shell_command_launcher/__init__.py
shell_command_launcher/shell_command_launcher.py
shell_command_launcher/version.py
shell_command_launcher-1.1.0.dist-info/LICENSE
shell_command_launcher-1.1.0.dist-info/METADATA
shell_command_launcher-1.1.0.dist-info/WHEEL
shell_command_launcher-1.1.0.dist-info/entry_points.txt
shell_command_launcher-1.1.0.dist-info/top_level.txt
shell_command_launcher-1.1.0.dist-info/RECORD
